biosut/__init__.py
biosut/alter_bam.py
biosut/alter_seq.py
biosut/bamutil.py
biosut/bioalign.py
biosut/blastutil.py
biosut/go_exe.py
biosut/go_file.py
biosut/go_path.py
biosut/io_bam.py
biosut/io_seq.py
biosut/readseq.py
biosut/sequtil.py
biosut/system.py
biosut/aligner/__init__.py
biosut/aligner/_blast.py
biosut/aligner/_diamond.py
biosut-1.0.0.dist-info/METADATA
biosut-1.0.0.dist-info/WHEEL
biosut-1.0.0.dist-info/top_level.txt
biosut-1.0.0.dist-info/RECORD
