Metadata-Version: 2.1
Name: biosut
Version: 1.0.0
Summary: bioutil library for bio related bioinformatics operations.
Home-page: https://github.com/jlli6t/biosut
Author: M.M Jie Li
Author-email: mm.jlli6t@gmail.com
License: UNKNOWN
Platform: UNKNOWN
Classifier: License :: OSI Approved :: GNU General Public License v3 (GPLv3)
Classifier: Programming Language :: Python :: 3 :: Only
Classifier: Operating System :: Unix
Requires-Python: >=3.6
